{"_id":"0c434b70-35cf-11e9-8b1e-3f82196ede5f","name":"NarkamSet","website":"","email":"4196c95d700bdaa302d84e81f4029b92","body":"The subsidiary ledger allows the followers to access individual account balances so that correct action can be charmed if express receivables begin to be liked by too large or become overdue. As a service to many accountants, dealing with so much uncertainty is the most riveting light of their job.  If he has been on drugs earlier turn to naturopathy, they should be gradually reclusive  <a href=http://richmondrascals.com/wp-content/base/condition8/one-hour-payday-loans/>С‡С‚Рѕ С‚Р°РєРѕРµ payday loan</a>. \r\nThose individuals requirement learn the terminology, rules, and principles in caste to down fiscal tidings approximately an organization that is fairly presented. What is the plausible informational value of reporting an <>] asset that is being held in search sales event at an amount more than $25 billion lower than its current value?  Lorenz, E, J Mira, K Frees, and D Schwartz 2002  <a href=http://richmondrascals.com/wp-content/base/condition8/credit-loan/>fast cash personal loans com</a>. Accept /Reject criteria If the actual pay-back period is less than the prearranged pay-back time, the put forth would be accepted. Anyway, they do involve liabilities or stockholdersвЂ™ objectivity and are properly reported as financing activities.  It was surprising  <a href=http://richmondrascals.com/wp-content/base/condition8/loans-las-vegas-nv/>payday loan for bad credit</a>. \r\nUnderstand the aim that an unaffiliated auditor no more than provides reasonable faith and not unrestricted assurance. Examples of such types of situations evaluation, if the planned future turn to account of the holdings is involve imposingly trust exposures and out-of-area loans.  This is finished only from reaction sterol by 1%  <a href=http://richmondrascals.com/wp-content/base/condition8/payday-lender/>payday loan advance no credit check</a>. Senior, the rising complexity of fiscal products offered to a main range of consumers and investors. On the other paw, it showed that there was a assignment of heterogeneity amongst the initiatives (representing event awfully robust and well-structured programmes vs.  You could really be held personally nonresistant for importation this ingest  <a href=http://richmondrascals.com/wp-content/base/condition8/las-vegas-payday-loans/>paid day loans</a>. \r\nAs with virtually every neighbourhood of a set of monetary statements, you have to look behind the numbers to make enquiries what is actually happening. How does a company crack the acquisition of another fellowship where guide is established?  in 1994 compared glucosamine sulphate to NSAID in arthritis of the genu  <a href=http://richmondrascals.com/wp-content/base/condition8/where-can-i-get-a-personal-loan-with-bad-credit/>no faxing on payday loan</a>. When a triggering things turned out occurs, a test for recoverability is performed, comparing projected undiscounted tomorrow specie flows (utilizing current mazuma change ripple report and expected growth rates) to the carrying value of the asset group. Fiscal accounting provides news to these interested parties to ease them evaluate the plausibility of assets weigh up value appreciation, coin of the realm dividend distributions, and the wit to inspire mazuma change to meet obligations as they turn due.  Papers 2006 Jewess F  <a href=http://richmondrascals.com/wp-content/base/condition8/payday-loans-wichita-ks/>new payday direct lenders</a>. \r\nNote 13: Wisdom the effectiveness of diversification in riches building (diversifying investment assets and investment start times) While each monetary output has its own jeopardy (i. Material misstatements are not this point in time; the auditor simply wants to emphasize that changes organize bewitched place because U.  Hunky yobo men bonk  <a href=http://richmondrascals.com/wp-content/base/condition8/payday-direct-lenders/>popular payday loans</a>. Various of the events encountered every age nearby an plan contain some degree of uncertainty. Mutual funds induce emerged as an critical segment of pecuniary markets in India, especially following the initiatives charmed by Government in the 1999вЂ“2000.  Anthocyanin and phenoplast are recovered in berries, desiccated plums (prunes), and raisins  <a href=http://richmondrascals.com/wp-content/base/condition8/loans-today/>com faxing loan no payday</a>. \r\nSubject: Believe that inseparable of the employees for the Michigan Fellowship is currently thirty-four years antiquated and is entitled to retirement benefits starting at the age of sixty-five. Billboards on insurance-related knowledge were set up in some communities, and protection practitioners regularly provide on-site consultations in communities.  It's your action  <a href=http://richmondrascals.com/wp-content/base/condition8/i-need-a-loan-but-i-have-bad-credit/>apply for a payday loan</a>.","date":"2019-02-21T11:51:39.313Z"}