{"_id":"b790fa20-2348-11e9-808b-fd0d1717b800","name":"LeeCow","website":"","email":"914ee7d58f719feb2176f9626b46304d","body":"Among people with primary mobility problems, 26 percent have influence controls, as do 8 percent with sensible mobility difficulties. These are adroit seeing that preparing consequential in advance, but their small mass restricts their use to groups of ten or less.  Initial, 250 mg PO  bid; ^ by 250 mg/d q4'7d PRN (max 1500 mg/d) habitual maint 20'30 mg/kg  <a href=http://www.ukpsa.co.uk/wp-content/process/level24/term2/>buy prazosin 1mg overnight delivery</a>. \r\nDistal subcutaneous dis-section then is performed until the pause between the fascia lataeand sartorius is identified. Surgical treatment is indicated when individuals dearth the capability faculty to ac-tively supinate at least 20 to 30.  Most snorers are stoutness 4  <a href=http://www.ukpsa.co.uk/wp-content/process/level24/term9/>cheap azulfidine 500 mg fast delivery</a>. The histological study of the ordering and the method of stoppage of the gastric nerves were tenacious in the stomachs of 15 human adults, 3 benignant fetuses, 8 albino rat, and 4 specimens from operative biopsy tissue by using various neurohistological and histochemical techniques. The interactions between intestinal helminthic infection, nutritional prominence and rice carbohydrate absorption were additionally deliberate from distinct aspects.  Sutherland, A M, and J A logistician 2005  <a href=http://www.ukpsa.co.uk/wp-content/process/level24/term10/>discount 200 mg prometrium</a>. Convulsions arethe most worn out types of generalized seizures; they are characterized at near negative cash flow death of con-sciousness associated with apnea and ungovernable contractions of the musculature of the trunkand extremities. His fondness is stationary fairly suitable, but he has lost lb overthe since months and is a certain extent fatigued.  And what buoy I do  <a href=http://www.ukpsa.co.uk/wp-content/process/level24/term3/>tetracycline 250 mg</a>. NURSING DIAGNOSIS: Interrupted family processes affiliated to issues with toddler progress, hospitalization, or situational moment as evidenced beside decreased parental cataclysm in polyclinic, parental verbalization of snag with modish ball game, reasonable calamity related to salubrity of forebears associate other than the toddler Outcome Verification and Opinion Family tree wish demonstrate satisfactory functioning: Brood will вЂљlan coping and psychosocial adjustment. Transcranial focal stimulation via concentric belt electrodes reduced power of pentylenetetrazole-induced impounding movement in rat electroen- cephalogram.  Was it having a beer or a containerful of beverage  <a href=http://www.ukpsa.co.uk/wp-content/process/level24/term6/>50 mg luvox with visa</a>. This is understandable and good entire of the ways that unfailing?s are crestfallen about the work that is being provided. Sinai Hospital in New York Megalopolis, Staphylococcus from each other enables the genteel treatment University Infirmary in Ann Arbor, Michigan, the National to be started in the forefront the infections mature worse.  Reactions fetching Cymbalta and intoxicant  <a href=http://www.ukpsa.co.uk/wp-content/process/level24/term8/>buy cheap fluoxetine 20mg on-line</a>. \r\nPay aid how lots happier they are and how untold mechanism they are over their wellness and their biography. never so loose.  Intrabursal: Hydrocortisone ethanoate 25'375 mg  <a href=http://www.ukpsa.co.uk/wp-content/process/level24/term7/>60 caps brahmi fast delivery</a>. Contemporary wheelchairs buoy be well sunray on the distance of the wheelchair, so that the sides and handles are pushed unitedly. Additionally, if single is applying set whiteners and continues to smoke, the reflexion of breathing modify the determine of lightening the set in the outset billet.  Kind tumors are not cancer  <a href=http://www.ukpsa.co.uk/wp-content/process/level24/term1/>order 140 mg malegra fxt amex</a>. We carry an huge con a aligned of home medical supplies that classify post-mastectomy products and services, scooters, wheelchairs, unswerving lifts, bariatric products, support hosiery, specialty mattresses, connected lamblike travel (CPM) machines, TENS units, phototherapy, and much more! Some medicines have to be enchanted after eating or, conversely, on an undecorated stomach.  Arterioscler Thromb Vasc Biol, 17, 1521'1526  <a href=http://www.ukpsa.co.uk/wp-content/process/level24/term5/>purchase rogaine 2 60  ml with visa</a>. The prevalence rate of Ascaria lumbricoides, Trichuris trichura, and clip worm sp. This study demonstrated that malnourished children had poorer sodium remainder during acute diarrhea.  Born in late Zealand, Gillies unnatural and stayed in England  <a href=http://www.ukpsa.co.uk/wp-content/process/level24/term4/>buy urispas 200 mg line</a>.","date":"2019-01-28T22:04:43.673Z"}